{
  "fileName": "MissionFailPopup_Continue",
  "filePath": "E:/AIMED/FantaPuzzle/PuzzleAutomation2/Assets\\Resources\\Prefabs\\Popup\\MissionFailPopup_Continue.prefab",
  "fileType": "prefab",
  "gameObjectCount": 73,
  "canvases": [],
  "canvasScalers": [],
  "canvasGroups": [],
  "buttons": [
    {
      "type": "Button",
      "fileID": "944542088802158007",
      "m_Colors": {
        "m_NormalColor": {
          "r": 1.0,
          "g": 1.0,
          "b": 1.0,
          "a": 1.0
        },
        "m_HighlightedColor": {
          "r": 0.9607843,
          "g": 0.9607843,
          "b": 0.9607843,
          "a": 1.0
        },
        "m_PressedColor": {
          "r": 0.78431374,
          "g": 0.78431374,
          "b": 0.78431374,
          "a": 1.0
        },
        "m_SelectedColor": {
          "r": 0.9607843,
          "g": 0.9607843,
          "b": 0.9607843,
          "a": 1.0
        },
        "m_DisabledColor": {
          "r": 0.78431374,
          "g": 0.78431374,
          "b": 0.78431374,
          "a": 0.5019608
        }
      },
      "m_Navigation": {
        "m_Mode": 3
      },
      "m_Interactable": 1,
      "gameObjectName": "Restart",
      "rectSize": {
        "x": 284.5,
        "y": 149.5
      },
      "anchoredPosition": {
        "x": 0.0,
        "y": -305.0
      },
      "anchorMin": {
        "x": 0.5,
        "y": 0.5
      },
      "anchorMax": {
        "x": 0.5,
        "y": 0.5
      },
      "sourceFile": "MissionFailPopup_Continue"
    },
    {
      "type": "Button",
      "fileID": "4075269880658146847",
      "m_Colors": {
        "m_NormalColor": {
          "r": 1.0,
          "g": 1.0,
          "b": 1.0,
          "a": 1.0
        },
        "m_HighlightedColor": {
          "r": 0.9607843,
          "g": 0.9607843,
          "b": 0.9607843,
          "a": 1.0
        },
        "m_PressedColor": {
          "r": 0.78431374,
          "g": 0.78431374,
          "b": 0.78431374,
          "a": 1.0
        },
        "m_SelectedColor": {
          "r": 0.9607843,
          "g": 0.9607843,
          "b": 0.9607843,
          "a": 1.0
        },
        "m_DisabledColor": {
          "r": 0.78431374,
          "g": 0.78431374,
          "b": 0.78431374,
          "a": 0.5019608
        }
      },
      "m_Navigation": {
        "m_Mode": 3
      },
      "m_Interactable": 1,
      "gameObjectName": "Shop",
      "rectSize": {
        "x": 512.0,
        "y": 512.0
      },
      "anchoredPosition": {
        "x": -323.0,
        "y": 796.0
      },
      "anchorMin": {
        "x": 0.5,
        "y": 0.5
      },
      "anchorMax": {
        "x": 0.5,
        "y": 0.5
      },
      "sourceFile": "MissionFailPopup_Continue"
    },
    {
      "type": "Button",
      "fileID": "5702753521654246495",
      "m_Colors": {
        "m_NormalColor": {
          "r": 1.0,
          "g": 1.0,
          "b": 1.0,
          "a": 1.0
        },
        "m_HighlightedColor": {
          "r": 0.9607843,
          "g": 0.9607843,
          "b": 0.9607843,
          "a": 1.0
        },
        "m_PressedColor": {
          "r": 0.78431374,
          "g": 0.78431374,
          "b": 0.78431374,
          "a": 1.0
        },
        "m_SelectedColor": {
          "r": 0.9607843,
          "g": 0.9607843,
          "b": 0.9607843,
          "a": 1.0
        },
        "m_DisabledColor": {
          "r": 0.78431374,
          "g": 0.78431374,
          "b": 0.78431374,
          "a": 0.5019608
        }
      },
      "m_Navigation": {
        "m_Mode": 3
      },
      "m_Interactable": 1,
      "gameObjectName": "OpenAds",
      "rectSize": {
        "x": 915.0,
        "y": 230.0
      },
      "anchoredPosition": {
        "x": 0.0,
        "y": -255.0
      },
      "anchorMin": {
        "x": 0.5,
        "y": 0.5
      },
      "anchorMax": {
        "x": 0.5,
        "y": 0.5
      },
      "sourceFile": "MissionFailPopup_Continue"
    },
    {
      "type": "Button",
      "fileID": "8291899343638176678",
      "m_Colors": {
        "m_NormalColor": {
          "r": 1.0,
          "g": 1.0,
          "b": 1.0,
          "a": 1.0
        },
        "m_HighlightedColor": {
          "r": 0.9607843,
          "g": 0.9607843,
          "b": 0.9607843,
          "a": 1.0
        },
        "m_PressedColor": {
          "r": 0.78431374,
          "g": 0.78431374,
          "b": 0.78431374,
          "a": 1.0
        },
        "m_SelectedColor": {
          "r": 0.9607843,
          "g": 0.9607843,
          "b": 0.9607843,
          "a": 1.0
        },
        "m_DisabledColor": {
          "r": 0.78431374,
          "g": 0.78431374,
          "b": 0.78431374,
          "a": 0.5019608
        }
      },
      "m_Navigation": {
        "m_Mode": 3
      },
      "m_Interactable": 1,
      "gameObjectName": "Continue",
      "rectSize": {
        "x": 431.0,
        "y": 165.0
      },
      "anchoredPosition": {
        "x": 0.0,
        "y": -200.0
      },
      "anchorMin": {
        "x": 0.5,
        "y": 0.5
      },
      "anchorMax": {
        "x": 0.5,
        "y": 0.5
      },
      "sourceFile": "MissionFailPopup_Continue"
    },
    {
      "type": "Button",
      "fileID": "4453970694362170248",
      "m_Colors": {
        "m_NormalColor": {
          "r": 1.0,
          "g": 1.0,
          "b": 1.0,
          "a": 1.0
        },
        "m_HighlightedColor": {
          "r": 0.9607843,
          "g": 0.9607843,
          "b": 0.9607843,
          "a": 1.0
        },
        "m_PressedColor": {
          "r": 0.78431374,
          "g": 0.78431374,
          "b": 0.78431374,
          "a": 1.0
        },
        "m_SelectedColor": {
          "r": 0.9607843,
          "g": 0.9607843,
          "b": 0.9607843,
          "a": 1.0
        },
        "m_DisabledColor": {
          "r": 0.78431374,
          "g": 0.78431374,
          "b": 0.78431374,
          "a": 0.5019608
        }
      },
      "m_Navigation": {
        "m_Mode": 3
      },
      "m_Interactable": 1,
      "gameObjectName": "OpenAds",
      "rectSize": {
        "x": 306.7,
        "y": 132.0
      },
      "anchoredPosition": {
        "x": 349.7,
        "y": -4.0
      },
      "anchorMin": {
        "x": 0.5,
        "y": 0.5
      },
      "anchorMax": {
        "x": 0.5,
        "y": 0.5
      },
      "sourceFile": "MissionFailPopup_Continue"
    },
    {
      "type": "Button",
      "fileID": "4731634628098700720",
      "m_Colors": {
        "m_NormalColor": {
          "r": 1.0,
          "g": 1.0,
          "b": 1.0,
          "a": 1.0
        },
        "m_HighlightedColor": {
          "r": 0.9607843,
          "g": 0.9607843,
          "b": 0.9607843,
          "a": 1.0
        },
        "m_PressedColor": {
          "r": 0.78431374,
          "g": 0.78431374,
          "b": 0.78431374,
          "a": 1.0
        },
        "m_SelectedColor": {
          "r": 0.9607843,
          "g": 0.9607843,
          "b": 0.9607843,
          "a": 1.0
        },
        "m_DisabledColor": {
          "r": 0.78431374,
          "g": 0.78431374,
          "b": 0.78431374,
          "a": 0.5019608
        }
      },
      "m_Navigation": {
        "m_Mode": 3
      },
      "m_Interactable": 1,
      "gameObjectName": "CloseBtn",
      "rectSize": {
        "x": 128.0,
        "y": 128.0
      },
      "anchoredPosition": {
        "x": 463.0,
        "y": 662.0
      },
      "anchorMin": {
        "x": 0.5,
        "y": 0.5
      },
      "anchorMax": {
        "x": 0.5,
        "y": 0.5
      },
      "sourceFile": "MissionFailPopup_Continue"
    },
    {
      "type": "Button",
      "fileID": "7946632581177219455",
      "m_Colors": {
        "m_NormalColor": {
          "r": 1.0,
          "g": 1.0,
          "b": 1.0,
          "a": 1.0
        },
        "m_HighlightedColor": {
          "r": 0.9607843,
          "g": 0.9607843,
          "b": 0.9607843,
          "a": 1.0
        },
        "m_PressedColor": {
          "r": 0.78431374,
          "g": 0.78431374,
          "b": 0.78431374,
          "a": 1.0
        },
        "m_SelectedColor": {
          "r": 0.9607843,
          "g": 0.9607843,
          "b": 0.9607843,
          "a": 1.0
        },
        "m_DisabledColor": {
          "r": 0.78431374,
          "g": 0.78431374,
          "b": 0.78431374,
          "a": 0.5019608
        }
      },
      "m_Navigation": {
        "m_Mode": 3
      },
      "m_Interactable": 1,
      "gameObjectName": "bg",
      "rectSize": {
        "x": 903.0,
        "y": 215.0
      },
      "anchoredPosition": {
        "x": 0.0,
        "y": -351.0
      },
      "anchorMin": {
        "x": 0.5,
        "y": 0.5
      },
      "anchorMax": {
        "x": 0.5,
        "y": 0.5
      },
      "sourceFile": "MissionFailPopup_Continue"
    },
    {
      "type": "Button",
      "fileID": "6522498819324128625",
      "m_Colors": {
        "m_NormalColor": {
          "r": 1.0,
          "g": 1.0,
          "b": 1.0,
          "a": 1.0
        },
        "m_HighlightedColor": {
          "r": 0.9607843,
          "g": 0.9607843,
          "b": 0.9607843,
          "a": 1.0
        },
        "m_PressedColor": {
          "r": 0.78431374,
          "g": 0.78431374,
          "b": 0.78431374,
          "a": 1.0
        },
        "m_SelectedColor": {
          "r": 0.9607843,
          "g": 0.9607843,
          "b": 0.9607843,
          "a": 1.0
        },
        "m_DisabledColor": {
          "r": 0.78431374,
          "g": 0.78431374,
          "b": 0.78431374,
          "a": 0.5019608
        }
      },
      "m_Navigation": {
        "m_Mode": 3
      },
      "m_Interactable": 1,
      "gameObjectName": "Continue_Ads",
      "rectSize": {
        "x": 434.0,
        "y": 170.0
      },
      "anchoredPosition": {
        "x": 0.0,
        "y": -200.0
      },
      "anchorMin": {
        "x": 0.5,
        "y": 0.5
      },
      "anchorMax": {
        "x": 0.5,
        "y": 0.5
      },
      "sourceFile": "MissionFailPopup_Continue"
    }
  ],
  "scrollRects": [],
  "images": [
    {
      "type": "Image",
      "fileID": "3494696707538201326",
      "m_Type": 0,
      "m_Color": {
        "r": 1.0,
        "g": 1.0,
        "b": 1.0,
        "a": 1.0
      },
      "m_Sprite": {
        "fileID": 849846990632842826,
        "guid": "60d46764f4ded4577a9cd467f0cd7844",
        "type": 3
      },
      "m_RaycastTarget": 1,
      "gameObjectName": "Restart",
      "rectSize": {
        "x": 284.5,
        "y": 149.5
      },
      "anchoredPosition": {
        "x": 0.0,
        "y": -305.0
      },
      "anchorMin": {
        "x": 0.5,
        "y": 0.5
      },
      "anchorMax": {
        "x": 0.5,
        "y": 0.5
      },
      "sourceFile": "MissionFailPopup_Continue"
    },
    {
      "type": "Image",
      "fileID": "5149275975269267451",
      "m_Type": 0,
      "m_Color": {
        "r": 1.0,
        "g": 1.0,
        "b": 1.0,
        "a": 1.0
      },
      "m_Sprite": {
        "fileID": 21300000,
        "guid": "4e087525e6b034cefa5981e4654a5f84",
        "type": 3
      },
      "m_RaycastTarget": 1,
      "gameObjectName": "BG",
      "rectSize": {
        "x": 512.0,
        "y": 512.0
      },
      "anchoredPosition": {
        "x": 0.0,
        "y": 0.0
      },
      "anchorMin": {
        "x": 0.5,
        "y": 0.5
      },
      "anchorMax": {
        "x": 0.5,
        "y": 0.5
      },
      "sourceFile": "MissionFailPopup_Continue"
    },
    {
      "type": "Image",
      "fileID": "2314600107223766143",
      "m_Type": 0,
      "m_Color": {
        "r": 1.0,
        "g": 1.0,
        "b": 1.0,
        "a": 1.0
      },
      "m_Sprite": {
        "fileID": 21300000,
        "guid": "c0b76f4cbc481459285834fa735981e6",
        "type": 3
      },
      "m_RaycastTarget": 1,
      "gameObjectName": "Image",
      "rectSize": {
        "x": 126.1,
        "y": 126.1
      },
      "anchoredPosition": {
        "x": 144.0,
        "y": 0.0
      },
      "anchorMin": {
        "x": 0.5,
        "y": 0.5
      },
      "anchorMax": {
        "x": 0.5,
        "y": 0.5
      },
      "sourceFile": "MissionFailPopup_Continue"
    },
    {
      "type": "Image",
      "fileID": "5036450173768665173",
      "m_Type": 0,
      "m_Color": {
        "r": 1.0,
        "g": 1.0,
        "b": 1.0,
        "a": 1.0
      },
      "m_Sprite": {
        "fileID": 21300000,
        "guid": "4e087525e6b034cefa5981e4654a5f84",
        "type": 3
      },
      "m_RaycastTarget": 1,
      "gameObjectName": "BG",
      "rectSize": {
        "x": 512.0,
        "y": 512.0
      },
      "anchoredPosition": {
        "x": 0.0,
        "y": 0.0
      },
      "anchorMin": {
        "x": 0.5,
        "y": 0.5
      },
      "anchorMax": {
        "x": 0.5,
        "y": 0.5
      },
      "sourceFile": "MissionFailPopup_Continue"
    },
    {
      "type": "Image",
      "fileID": "4893387146419053039",
      "m_Type": 0,
      "m_Color": {
        "r": 1.0,
        "g": 1.0,
        "b": 1.0,
        "a": 1.0
      },
      "m_Sprite": {
        "fileID": 21300000,
        "guid": "68a2683078ca84b87a88dc4f21d034a9",
        "type": 3
      },
      "m_RaycastTarget": 1,
      "gameObjectName": "Shop",
      "rectSize": {
        "x": 512.0,
        "y": 512.0
      },
      "anchoredPosition": {
        "x": -323.0,
        "y": 796.0
      },
      "anchorMin": {
        "x": 0.5,
        "y": 0.5
      },
      "anchorMax": {
        "x": 0.5,
        "y": 0.5
      },
      "sourceFile": "MissionFailPopup_Continue"
    },
    {
      "type": "Image",
      "fileID": "7266036268617724034",
      "m_Type": 0,
      "m_Color": {
        "r": 1.0,
        "g": 1.0,
        "b": 1.0,
        "a": 1.0
      },
      "m_Sprite": {
        "fileID": 21300000,
        "guid": "8ff720204eaf04fa980ea8c7fe09905b",
        "type": 3
      },
      "m_RaycastTarget": 1,
      "gameObjectName": "Gold",
      "rectSize": {
        "x": 160.9,
        "y": 155.4
      },
      "anchoredPosition": {
        "x": -133.0,
        "y": 1.0
      },
      "anchorMin": {
        "x": 0.5,
        "y": 0.5
      },
      "anchorMax": {
        "x": 0.5,
        "y": 0.5
      },
      "sourceFile": "MissionFailPopup_Continue"
    },
    {
      "type": "Image",
      "fileID": "6917400203500258987",
      "m_Type": 0,
      "m_Color": {
        "r": 1.0,
        "g": 1.0,
        "b": 1.0,
        "a": 1.0
      },
      "m_Sprite": {
        "fileID": 21300000,
        "guid": "4e087525e6b034cefa5981e4654a5f84",
        "type": 3
      },
      "m_RaycastTarget": 1,
      "gameObjectName": "BG",
      "rectSize": {
        "x": 512.0,
        "y": 512.0
      },
      "anchoredPosition": {
        "x": 0.0,
        "y": 0.0
      },
      "anchorMin": {
        "x": 0.5,
        "y": 0.5
      },
      "anchorMax": {
        "x": 0.5,
        "y": 0.5
      },
      "sourceFile": "MissionFailPopup_Continue"
    },
    {
      "type": "Image",
      "fileID": "120588364951659840",
      "m_Type": 0,
      "m_Color": {
        "r": 1.0,
        "g": 1.0,
        "b": 1.0,
        "a": 1.0
      },
      "m_Sprite": {
        "fileID": 2067646171788204918,
        "guid": "1fe99c5b19d55413fa29385b5dd01bc8"
      },
      "m_RaycastTarget": 0,
      "gameObjectName": "Box",
      "rectSize": {
        "x": 416.0,
        "y": 354.8
      },
      "anchoredPosition": {
        "x": 41.0,
        "y": 44.0
      },
      "anchorMin": {
        "x": 0.5,
        "y": 0.5
      },
      "anchorMax": {
        "x": 0.5,
        "y": 0.5
      },
      "sourceFile": "MissionFailPopup_Continue"
    },
    {
      "type": "Image",
      "fileID": "7436107082962465910",
      "m_Type": 0,
      "m_Color": {
        "r": 1.0,
        "g": 1.0,
        "b": 1.0,
        "a": 1.0
      },
      "m_Sprite": {
        "fileID": 21300000,
        "guid": "c21d23e9cdc7c4dbeb705eb3903b6c60",
        "type": 3
      },
      "m_RaycastTarget": 0,
      "gameObjectName": "Move",
      "rectSize": {
        "x": 167.93,
        "y": 167.9
      },
      "anchoredPosition": {
        "x": 0.0,
        "y": 0.0
      },
      "anchorMin": {
        "x": 0.5,
        "y": 0.5
      },
      "anchorMax": {
        "x": 0.5,
        "y": 0.5
      },
      "sourceFile": "MissionFailPopup_Continue"
    },
    {
      "type": "Image",
      "fileID": "5196566892488128032",
      "m_Type": 0,
      "m_Color": {
        "r": 1.0,
        "g": 1.0,
        "b": 1.0,
        "a": 1.0
      },
      "m_Sprite": {
        "fileID": 21300000,
        "guid": "8605b8567af7c48449b99f3d02c51320",
        "type": 3
      },
      "m_RaycastTarget": 1,
      "gameObjectName": "Item",
      "rectSize": {
        "x": 89.787,
        "y": 89.8
      },
      "anchoredPosition": {
        "x": -109.0,
        "y": 18.0
      },
      "anchorMin": {
        "x": 0.5,
        "y": 0.5
      },
      "anchorMax": {
        "x": 0.5,
        "y": 0.5
      },
      "sourceFile": "MissionFailPopup_Continue"
    },
    {
      "type": "Image",
      "fileID": "7620701580061209953",
      "m_Type": 0,
      "m_Color": {
        "r": 1.0,
        "g": 1.0,
        "b": 1.0,
        "a": 1.0
      },
      "m_Sprite": {
        "fileID": 21300000,
        "guid": "99368406a3a584e2e8d1392b95381ecb",
        "type": 3
      },
      "m_RaycastTarget": 0,
      "gameObjectName": "Box_Effect (1)",
      "rectSize": {
        "x": 794.7,
        "y": 264.9
      },
      "anchoredPosition": {
        "x": 38.0,
        "y": 41.0
      },
      "anchorMin": {
        "x": 0.5,
        "y": 0.5
      },
      "anchorMax": {
        "x": 0.5,
        "y": 0.5
      },
      "sourceFile": "MissionFailPopup_Continue"
    },
    {
      "type": "Image",
      "fileID": "3720861034341195670",
      "m_Type": 0,
      "m_Color": {
        "r": 1.0,
        "g": 1.0,
        "b": 1.0,
        "a": 1.0
      },
      "m_Sprite": {
        "fileID": 21300000,
        "guid": "9b2b2d57af09e4a7e9509672aeb5523f",
        "type": 3
      },
      "m_RaycastTarget": 1,
      "gameObjectName": "Item",
      "rectSize": {
        "x": 82.1,
        "y": 82.1
      },
      "anchoredPosition": {
        "x": -107.0,
        "y": 16.0
      },
      "anchorMin": {
        "x": 0.5,
        "y": 0.5
      },
      "anchorMax": {
        "x": 0.5,
        "y": 0.5
      },
      "sourceFile": "MissionFailPopup_Continue"
    },
    {
      "type": "Image",
      "fileID": "4537665090578342212",
      "m_Type": 1,
      "m_Color": {
        "r": 0.0,
        "g": 0.0,
        "b": 0.0,
        "a": 0.9019608
      },
      "m_Sprite": {
        "fileID": 10907,
        "guid": "0000000000000000f000000000000000",
        "type": 0
      },
      "m_RaycastTarget": 1,
      "gameObjectName": "Panel",
      "rectSize": {
        "x": 3000.0,
        "y": 3000.0
      },
      "anchoredPosition": {
        "x": 0.0,
        "y": 0.0
      },
      "anchorMin": {
        "x": 0.5,
        "y": 0.5
      },
      "anchorMax": {
        "x": 0.5,
        "y": 0.5
      },
      "sourceFile": "MissionFailPopup_Continue"
    },
    {
      "type": "Image",
      "fileID": "4537665091062163692",
      "m_Type": 0,
      "m_Color": {
        "r": 1.0,
        "g": 1.0,
        "b": 1.0,
        "a": 1.0
      },
      "m_Sprite": {
        "fileID": 21300000,
        "guid": "75c9da09e1e4144a28ddb6f505790ded",
        "type": 3
      },
      "m_RaycastTarget": 0,
      "gameObjectName": "Ads",
      "rectSize": {
        "x": 1024.0,
        "y": 1024.0
      },
      "anchoredPosition": {
        "x": 0.0,
        "y": 164.0
      },
      "anchorMin": {
        "x": 0.5,
        "y": 0.5
      },
      "anchorMax": {
        "x": 0.5,
        "y": 0.5
      },
      "sourceFile": "MissionFailPopup_Continue"
    },
    {
      "type": "Image",
      "fileID": "8312726144994727663",
      "m_Type": 0,
      "m_Color": {
        "r": 1.0,
        "g": 1.0,
        "b": 1.0,
        "a": 1.0
      },
      "m_Sprite": {
        "fileID": 21300000,
        "guid": "b502c1e09f56d48d1a07fcdb8c7030d2",
        "type": 3
      },
      "m_RaycastTarget": 1,
      "gameObjectName": "Restart",
      "rectSize": {
        "x": 90.0,
        "y": 90.0
      },
      "anchoredPosition": {
        "x": 0.0,
        "y": 0.0
      },
      "anchorMin": {
        "x": 0.5,
        "y": 0.5
      },
      "anchorMax": {
        "x": 0.5,
        "y": 0.5
      },
      "sourceFile": "MissionFailPopup_Continue"
    },
    {
      "type": "Image",
      "fileID": "6919094538637700169",
      "m_Type": 0,
      "m_Color": {
        "r": 1.0,
        "g": 1.0,
        "b": 1.0,
        "a": 1.0
      },
      "m_Sprite": {
        "fileID": 21300000,
        "guid": "4e087525e6b034cefa5981e4654a5f84",
        "type": 3
      },
      "m_RaycastTarget": 1,
      "gameObjectName": "BG",
      "rectSize": {
        "x": 512.0,
        "y": 512.0
      },
      "anchoredPosition": {
        "x": 0.0,
        "y": 0.0
      },
      "anchorMin": {
        "x": 0.5,
        "y": 0.5
      },
      "anchorMax": {
        "x": 0.5,
        "y": 0.5
      },
      "sourceFile": "MissionFailPopup_Continue"
    },
    {
      "type": "Image",
      "fileID": "7727286773863670583",
      "m_Type": 0,
      "m_Color": {
        "r": 1.0,
        "g": 1.0,
        "b": 1.0,
        "a": 1.0
      },
      "m_Sprite": {
        "fileID": 21300000,
        "guid": "20ccd6bc50304417ea834a3d801fd31c",
        "type": 3
      },
      "m_RaycastTarget": 1,
      "gameObjectName": "Item",
      "rectSize": {
        "x": 92.0,
        "y": 92.0
      },
      "anchoredPosition": {
        "x": -106.0,
        "y": 17.0
      },
      "anchorMin": {
        "x": 0.5,
        "y": 0.5
      },
      "anchorMax": {
        "x": 0.5,
        "y": 0.5
      },
      "sourceFile": "MissionFailPopup_Continue"
    },
    {
      "type": "Image",
      "fileID": "4432868890962291884",
      "m_Type": 0,
      "m_Color": {
        "r": 1.0,
        "g": 1.0,
        "b": 1.0,
        "a": 1.0
      },
      "m_Sprite": {
        "fileID": 21300000,
        "guid": "1ab7201c1dfad4116817fb4665ebcad6",
        "type": 3
      },
      "m_RaycastTarget": 0,
      "gameObjectName": "Box_Effect (2)",
      "rectSize": {
        "x": 1245.0,
        "y": 360.0
      },
      "anchoredPosition": {
        "x": 132.0,
        "y": 123.0
      },
      "anchorMin": {
        "x": 0.5,
        "y": 0.5
      },
      "anchorMax": {
        "x": 0.5,
        "y": 0.5
      },
      "sourceFile": "MissionFailPopup_Continue"
    },
    {
      "type": "Image",
      "fileID": "7131071107258717150",
      "m_Type": 0,
      "m_Color": {
        "r": 1.0,
        "g": 1.0,
        "b": 1.0,
        "a": 1.0
      },
      "m_Sprite": {
        "fileID": 21300000,
        "guid": "133ccaf0330484dc2bcd64aab4fea19c",
        "type": 3
      },
      "m_RaycastTarget": 0,
      "gameObjectName": "TitleBackground",
      "rectSize": {
        "x": 1024.0,
        "y": 1024.0
      },
      "anchoredPosition": {
        "x": 0.0,
        "y": 567.0
      },
      "anchorMin": {
        "x": 0.5,
        "y": 0.5
      },
      "anchorMax": {
        "x": 0.5,
        "y": 0.5
      },
      "sourceFile": "MissionFailPopup_Continue"
    },
    {
      "type": "Image",
      "fileID": "1481610285400229672",
      "m_Type": 0,
      "m_Color": {
        "r": 1.0,
        "g": 1.0,
        "b": 1.0,
        "a": 1.0
      },
      "m_Sprite": {
        "fileID": 4412336079460670110,
        "guid": "68160c32af78e480eac9e52a16d7f7ed"
      },
      "m_RaycastTarget": 0,
      "gameObjectName": "MoreMoveCount_Ads",
      "rectSize": {
        "x": 341.5,
        "y": 241.8
      },
      "anchoredPosition": {
        "x": 215.0,
        "y": 46.0
      },
      "anchorMin": {
        "x": 0.5,
        "y": 0.5
      },
      "anchorMax": {
        "x": 0.5,
        "y": 0.5
      },
      "sourceFile": "MissionFailPopup_Continue"
    },
    {
      "type": "Image",
      "fileID": "5554856500122077820",
      "m_Type": 0,
      "m_Color": {
        "r": 1.0,
        "g": 1.0,
        "b": 1.0,
        "a": 1.0
      },
      "m_Sprite": {
        "fileID": 21300000,
        "guid": "c21d23e9cdc7c4dbeb705eb3903b6c60",
        "type": 3
      },
      "m_RaycastTarget": 0,
      "gameObjectName": "Image",
      "rectSize": {
        "x": 167.93,
        "y": 167.9
      },
      "anchoredPosition": {
        "x": 0.0,
        "y": 0.0
      },
      "anchorMin": {
        "x": 0.5,
        "y": 0.5
      },
      "anchorMax": {
        "x": 0.5,
        "y": 0.5
      },
      "sourceFile": "MissionFailPopup_Continue"
    },
    {
      "type": "Image",
      "fileID": "761070427370337107",
      "m_Type": 0,
      "m_Color": {
        "r": 1.0,
        "g": 1.0,
        "b": 1.0,
        "a": 1.0
      },
      "m_Sprite": {
        "fileID": 21300000,
        "guid": "8ff720204eaf04fa980ea8c7fe09905b",
        "type": 3
      },
      "m_RaycastTarget": 0,
      "gameObjectName": "Image",
      "rectSize": {
        "x": 128.0,
        "y": 128.0
      },
      "anchoredPosition": {
        "x": -119.0,
        "y": 10.0
      },
      "anchorMin": {
        "x": 0.5,
        "y": 0.5
      },
      "anchorMax": {
        "x": 0.5,
        "y": 0.5
      },
      "sourceFile": "MissionFailPopup_Continue"
    },
    {
      "type": "Image",
      "fileID": "2609332968696094579",
      "m_Type": 0,
      "m_Color": {
        "r": 1.0,
        "g": 1.0,
        "b": 1.0,
        "a": 1.0
      },
      "m_Sprite": {
        "fileID": 21300000,
        "guid": "2d92a169488f740aba41494345a6ed72",
        "type": 3
      },
      "m_RaycastTarget": 0,
      "gameObjectName": "Image",
      "rectSize": {
        "x": 128.0,
        "y": 128.0
      },
      "anchoredPosition": {
        "x": -129.0,
        "y": 0.0
      },
      "anchorMin": {
        "x": 0.5,
        "y": 0.5
      },
      "anchorMax": {
        "x": 0.5,
        "y": 0.5
      },
      "sourceFile": "MissionFailPopup_Continue"
    },
    {
      "type": "Image",
      "fileID": "7780833970813208423",
      "m_Type": 1,
      "m_Color": {
        "r": 1.0,
        "g": 1.0,
        "b": 1.0,
        "a": 1.0
      },
      "m_Sprite": {
        "fileID": 5575179077785088333,
        "guid": "193a5905cd58c45fe8fe9134f9e260f9"
      },
      "m_RaycastTarget": 0,
      "gameObjectName": "BottomAds",
      "rectSize": {
        "x": 1080.0,
        "y": 191.0
      },
      "anchoredPosition": {
        "x": 0.0,
        "y": 0.0
      },
      "anchorMin": {
        "x": 0.5,
        "y": 0.0
      },
      "anchorMax": {
        "x": 0.5,
        "y": 0.0
      },
      "sourceFile": "MissionFailPopup_Continue"
    },
    {
      "type": "Image",
      "fileID": "7780833971219462627",
      "m_Type": 0,
      "m_Color": {
        "r": 1.0,
        "g": 1.0,
        "b": 1.0,
        "a": 1.0
      },
      "m_Sprite": {
        "fileID": 4412336079460670110,
        "guid": "68160c32af78e480eac9e52a16d7f7ed"
      },
      "m_RaycastTarget": 0,
      "gameObjectName": "MoreMoveCount",
      "rectSize": {
        "x": 341.5,
        "y": 241.8
      },
      "anchoredPosition": {
        "x": -215.0,
        "y": 46.0
      },
      "anchorMin": {
        "x": 0.5,
        "y": 0.5
      },
      "anchorMax": {
        "x": 0.5,
        "y": 0.5
      },
      "sourceFile": "MissionFailPopup_Continue"
    },
    {
      "type": "Image",
      "fileID": "7780833971615671388",
      "m_Type": 0,
      "m_Color": {
        "r": 1.0,
        "g": 1.0,
        "b": 1.0,
        "a": 1.0
      },
      "m_Sprite": {
        "fileID": -7838180443215080354,
        "guid": "a3ae827c2f0cf477d98e732e0d47d08a"
      },
      "m_RaycastTarget": 1,
      "gameObjectName": "Continue",
      "rectSize": {
        "x": 431.0,
        "y": 165.0
      },
      "anchoredPosition": {
        "x": 0.0,
        "y": -200.0
      },
      "anchorMin": {
        "x": 0.5,
        "y": 0.5
      },
      "anchorMax": {
        "x": 0.5,
        "y": 0.5
      },
      "sourceFile": "MissionFailPopup_Continue"
    },
    {
      "type": "Image",
      "fileID": "7780833972112485023",
      "m_Type": 0,
      "m_Color": {
        "r": 1.0,
        "g": 1.0,
        "b": 1.0,
        "a": 1.0
      },
      "m_Sprite": {
        "fileID": 783871198868519349,
        "guid": "26195f4347926410ebc19be979d79cc5",
        "type": 3
      },
      "m_RaycastTarget": 1,
      "gameObjectName": "OpenAds",
      "rectSize": {
        "x": 306.7,
        "y": 132.0
      },
      "anchoredPosition": {
        "x": 349.7,
        "y": -4.0
      },
      "anchorMin": {
        "x": 0.5,
        "y": 0.5
      },
      "anchorMax": {
        "x": 0.5,
        "y": 0.5
      },
      "sourceFile": "MissionFailPopup_Continue"
    },
    {
      "type": "Image",
      "fileID": "2781343958337014198",
      "m_Type": 0,
      "m_Color": {
        "r": 1.0,
        "g": 1.0,
        "b": 1.0,
        "a": 1.0
      },
      "m_Sprite": {
        "fileID": 21300000,
        "guid": "b331f1d30830747d29dcbb8af4d79942",
        "type": 3
      },
      "m_RaycastTarget": 0,
      "gameObjectName": "Box_Effect",
      "rectSize": {
        "x": 718.4,
        "y": 718.4
      },
      "anchoredPosition": {
        "x": 33.0,
        "y": 41.0
      },
      "anchorMin": {
        "x": 0.5,
        "y": 0.5
      },
      "anchorMax": {
        "x": 0.5,
        "y": 0.5
      },
      "sourceFile": "MissionFailPopup_Continue"
    },
    {
      "type": "Image",
      "fileID": "3768523238942452785",
      "m_Type": 0,
      "m_Color": {
        "r": 1.0,
        "g": 1.0,
        "b": 1.0,
        "a": 1.0
      },
      "m_Sprite": {
        "fileID": 21300000,
        "guid": "8ff720204eaf04fa980ea8c7fe09905b",
        "type": 3
      },
      "m_RaycastTarget": 1,
      "gameObjectName": "Item",
      "rectSize": {
        "x": 108.4,
        "y": 108.4
      },
      "anchoredPosition": {
        "x": -110.7,
        "y": 15.0
      },
      "anchorMin": {
        "x": 0.5,
        "y": 0.5
      },
      "anchorMax": {
        "x": 0.5,
        "y": 0.5
      },
      "sourceFile": "MissionFailPopup_Continue"
    },
    {
      "type": "Image",
      "fileID": "6989667757861837477",
      "m_Type": 0,
      "m_Color": {
        "r": 1.0,
        "g": 1.0,
        "b": 1.0,
        "a": 1.0
      },
      "m_Sprite": {
        "fileID": 21300000,
        "guid": "84ae387d48bfe4172a9519732d95d3a0",
        "type": 3
      },
      "m_RaycastTarget": 1,
      "gameObjectName": "CloseBtn",
      "rectSize": {
        "x": 128.0,
        "y": 128.0
      },
      "anchoredPosition": {
        "x": 463.0,
        "y": 662.0
      },
      "anchorMin": {
        "x": 0.5,
        "y": 0.5
      },
      "anchorMax": {
        "x": 0.5,
        "y": 0.5
      },
      "sourceFile": "MissionFailPopup_Continue"
    },
    {
      "type": "Image",
      "fileID": "4715553129137515249",
      "m_Type": 0,
      "m_Color": {
        "r": 1.0,
        "g": 1.0,
        "b": 1.0,
        "a": 1.0
      },
      "m_Sprite": {
        "fileID": 21300000,
        "guid": "75c9da09e1e4144a28ddb6f505790ded",
        "type": 3
      },
      "m_RaycastTarget": 0,
      "gameObjectName": "Package",
      "rectSize": {
        "x": 1024.0,
        "y": 1024.0
      },
      "anchoredPosition": {
        "x": 0.0,
        "y": 165.0
      },
      "anchorMin": {
        "x": 0.5,
        "y": 0.5
      },
      "anchorMax": {
        "x": 0.5,
        "y": 0.5
      },
      "sourceFile": "MissionFailPopup_Continue"
    },
    {
      "type": "Image",
      "fileID": "7621463065644270446",
      "m_Type": 0,
      "m_Color": {
        "r": 1.0,
        "g": 1.0,
        "b": 1.0,
        "a": 1.0
      },
      "m_Sprite": {
        "fileID": 7204579805090317955,
        "guid": "2d576056b47d440e68b80d3dd224342e"
      },
      "m_RaycastTarget": 1,
      "gameObjectName": "bg",
      "rectSize": {
        "x": 903.0,
        "y": 215.0
      },
      "anchoredPosition": {
        "x": 0.0,
        "y": -351.0
      },
      "anchorMin": {
        "x": 0.5,
        "y": 0.5
      },
      "anchorMax": {
        "x": 0.5,
        "y": 0.5
      },
      "sourceFile": "MissionFailPopup_Continue"
    },
    {
      "type": "Image",
      "fileID": "2376834539870424380",
      "m_Type": 0,
      "m_Color": {
        "r": 1.0,
        "g": 1.0,
        "b": 1.0,
        "a": 1.0
      },
      "m_Sprite": {
        "fileID": -7229724631080877923,
        "guid": "2e594e93b82534b6f8128eba3d7aadcd"
      },
      "m_RaycastTarget": 1,
      "gameObjectName": "Continue_Ads",
      "rectSize": {
        "x": 434.0,
        "y": 170.0
      },
      "anchoredPosition": {
        "x": 0.0,
        "y": -200.0
      },
      "anchorMin": {
        "x": 0.5,
        "y": 0.5
      },
      "anchorMax": {
        "x": 0.5,
        "y": 0.5
      },
      "sourceFile": "MissionFailPopup_Continue"
    }
  ],
  "texts": [
    {
      "type": "Text",
      "fileID": "8535501376945155312",
      "m_FontSize": 80.0,
      "m_Alignment": 4,
      "m_Color": {
        "r": 1.0,
        "g": 1.0,
        "b": 1.0,
        "a": 1.0
      },
      "gameObjectName": "PriceText",
      "rectSize": {
        "x": 861.0,
        "y": 153.0
      },
      "anchoredPosition": {
        "x": 0.0,
        "y": 0.0
      },
      "anchorMin": {
        "x": 0.5,
        "y": 0.5
      },
      "anchorMax": {
        "x": 0.5,
        "y": 0.5
      },
      "sourceFile": "MissionFailPopup_Continue"
    },
    {
      "type": "Text",
      "fileID": "6602621404879757917",
      "m_FontSize": 40.0,
      "m_Alignment": 4,
      "m_Color": {
        "r": 1.0,
        "g": 0.93483555,
        "b": 0.0,
        "a": 1.0
      },
      "m_Text": "10000",
      "gameObjectName": "Value",
      "rectSize": {
        "x": 146.05,
        "y": 45.16
      },
      "anchoredPosition": {
        "x": -3.61,
        "y": 13.35
      },
      "anchorMin": {
        "x": 0.5,
        "y": 0.5
      },
      "anchorMax": {
        "x": 0.5,
        "y": 0.5
      },
      "sourceFile": "MissionFailPopup_Continue"
    },
    {
      "type": "Text",
      "fileID": "7632916961917620233",
      "m_FontSize": 50.0,
      "m_Alignment": 4,
      "m_Color": {
        "r": 1.0,
        "g": 1.0,
        "b": 1.0,
        "a": 1.0
      },
      "m_Text": "COTINUE",
      "gameObjectName": "Text",
      "rectSize": {
        "x": 240.0,
        "y": 88.0
      },
      "anchoredPosition": {
        "x": 48.0,
        "y": -4.0
      },
      "anchorMin": {
        "x": 0.5,
        "y": 0.5
      },
      "anchorMax": {
        "x": 0.5,
        "y": 0.5
      },
      "sourceFile": "MissionFailPopup_Continue"
    },
    {
      "type": "Text",
      "fileID": "6892441378968450707",
      "m_FontSize": 40.0,
      "m_Alignment": 4,
      "m_Color": {
        "r": 1.0,
        "g": 0.93483555,
        "b": 0.0,
        "a": 1.0
      },
      "m_Text": "+4",
      "gameObjectName": "Value",
      "rectSize": {
        "x": 146.05,
        "y": 45.16
      },
      "anchoredPosition": {
        "x": -3.61,
        "y": 13.35
      },
      "anchorMin": {
        "x": 0.5,
        "y": 0.5
      },
      "anchorMax": {
        "x": 0.5,
        "y": 0.5
      },
      "sourceFile": "MissionFailPopup_Continue"
    },
    {
      "type": "Text",
      "fileID": "8732918390435772854",
      "m_FontSize": 20.0,
      "m_Alignment": 0,
      "m_Color": {
        "r": 1.0,
        "g": 1.0,
        "b": 1.0,
        "a": 1.0
      },
      "gameObjectName": "HeadLine",
      "rectSize": {
        "x": 438.0,
        "y": 35.0
      },
      "anchoredPosition": {
        "x": -119.0,
        "y": 308.0
      },
      "anchorMin": {
        "x": 0.5,
        "y": 0.5
      },
      "anchorMax": {
        "x": 0.5,
        "y": 0.5
      },
      "sourceFile": "MissionFailPopup_Continue"
    },
    {
      "type": "Text",
      "fileID": "4537665090768778520",
      "m_FontSize": 80.0,
      "m_Alignment": 4,
      "m_Color": {
        "r": 1.0,
        "g": 1.0,
        "b": 1.0,
        "a": 1.0
      },
      "m_Text": "OPEN",
      "gameObjectName": "CallToAction",
      "rectSize": {
        "x": 861.0,
        "y": 153.0
      },
      "anchoredPosition": {
        "x": 0.0,
        "y": 0.0
      },
      "anchorMin": {
        "x": 0.5,
        "y": 0.5
      },
      "anchorMax": {
        "x": 0.5,
        "y": 0.5
      },
      "sourceFile": "MissionFailPopup_Continue"
    },
    {
      "type": "Text",
      "fileID": "1791693713982593394",
      "m_FontSize": 20.0,
      "m_Alignment": 0,
      "m_Color": {
        "r": 1.0,
        "g": 1.0,
        "b": 1.0,
        "a": 1.0
      },
      "gameObjectName": "Body",
      "rectSize": {
        "x": 438.0,
        "y": 42.0
      },
      "anchoredPosition": {
        "x": -119.0,
        "y": 269.0
      },
      "anchorMin": {
        "x": 0.5,
        "y": 0.5
      },
      "anchorMax": {
        "x": 0.5,
        "y": 0.5
      },
      "sourceFile": "MissionFailPopup_Continue"
    },
    {
      "type": "Text",
      "fileID": "4784232379715540583",
      "m_FontSize": 30.0,
      "m_Alignment": 3,
      "m_Color": {
        "r": 1.0,
        "g": 1.0,
        "b": 1.0,
        "a": 1.0
      },
      "m_Text": "-500",
      "gameObjectName": "Text",
      "rectSize": {
        "x": 80.0,
        "y": 50.74
      },
      "anchoredPosition": {
        "x": -6.0,
        "y": -32.0
      },
      "anchorMin": {
        "x": 0.5,
        "y": 0.5
      },
      "anchorMax": {
        "x": 0.5,
        "y": 0.5
      },
      "sourceFile": "MissionFailPopup_Continue"
    },
    {
      "type": "Text",
      "fileID": "5851670113008988064",
      "m_FontSize": 50.0,
      "m_Alignment": 5,
      "m_Color": {
        "r": 0.9137255,
        "g": 0.8980392,
        "b": 0.75686276,
        "a": 1.0
      },
      "m_Text": "1000",
      "gameObjectName": "CurrentGold",
      "rectSize": {
        "x": 186.9,
        "y": 90.0
      },
      "anchoredPosition": {
        "x": 7.4,
        "y": -3.0
      },
      "anchorMin": {
        "x": 0.5,
        "y": 0.5
      },
      "anchorMax": {
        "x": 0.5,
        "y": 0.5
      },
      "sourceFile": "MissionFailPopup_Continue"
    },
    {
      "type": "Text",
      "fileID": "7339513168575409540",
      "m_FontSize": 70.0,
      "m_Alignment": 4,
      "m_Color": {
        "r": 0.64705884,
        "g": 0.7058824,
        "b": 0.6862745,
        "a": 1.0
      },
      "m_Text": "fail",
      "gameObjectName": "Text",
      "rectSize": {
        "x": 492.0,
        "y": 123.0
      },
      "anchoredPosition": {
        "x": 0.0,
        "y": 2.0
      },
      "anchorMin": {
        "x": 0.5,
        "y": 0.5
      },
      "anchorMax": {
        "x": 0.5,
        "y": 0.5
      },
      "sourceFile": "MissionFailPopup_Continue"
    },
    {
      "type": "Text",
      "fileID": "3787274439306392858",
      "m_FontSize": 40.0,
      "m_Alignment": 4,
      "m_Color": {
        "r": 1.0,
        "g": 0.93483555,
        "b": 0.0,
        "a": 1.0
      },
      "m_Text": "+4",
      "gameObjectName": "Value",
      "rectSize": {
        "x": 146.05,
        "y": 45.16
      },
      "anchoredPosition": {
        "x": -3.61,
        "y": 13.35
      },
      "anchorMin": {
        "x": 0.5,
        "y": 0.5
      },
      "anchorMax": {
        "x": 0.5,
        "y": 0.5
      },
      "sourceFile": "MissionFailPopup_Continue"
    },
    {
      "type": "Text",
      "fileID": "1852189322846775162",
      "m_FontSize": 70.0,
      "m_Alignment": 4,
      "m_Color": {
        "r": 0.9882353,
        "g": 0.8745098,
        "b": 0.003921569,
        "a": 1.0
      },
      "m_Text": "+5",
      "gameObjectName": "+5",
      "rectSize": {
        "x": 95.0,
        "y": 85.0
      },
      "anchoredPosition": {
        "x": 54.0,
        "y": 9.0
      },
      "anchorMin": {
        "x": 1.0,
        "y": 1.0
      },
      "anchorMax": {
        "x": 1.0,
        "y": 1.0
      },
      "sourceFile": "MissionFailPopup_Continue"
    },
    {
      "type": "Text",
      "fileID": "7780833971231776386",
      "m_FontSize": 20.0,
      "m_Alignment": 0,
      "m_Color": {
        "r": 1.0,
        "g": 1.0,
        "b": 1.0,
        "a": 1.0
      },
      "gameObjectName": "Body",
      "rectSize": {
        "x": 532.0,
        "y": 75.0
      },
      "anchoredPosition": {
        "x": -76.0,
        "y": -43.808987
      },
      "anchorMin": {
        "x": 0.5,
        "y": 0.5
      },
      "anchorMax": {
        "x": 0.5,
        "y": 0.5
      },
      "sourceFile": "MissionFailPopup_Continue"
    },
    {
      "type": "Text",
      "fileID": "7780833972176083992",
      "m_FontSize": 20.0,
      "m_Alignment": 0,
      "m_Color": {
        "r": 1.0,
        "g": 1.0,
        "b": 1.0,
        "a": 1.0
      },
      "gameObjectName": "HeadLine",
      "rectSize": {
        "x": 532.0,
        "y": 68.0
      },
      "anchoredPosition": {
        "x": -75.91399,
        "y": 28.0
      },
      "anchorMin": {
        "x": 0.5,
        "y": 0.5
      },
      "anchorMax": {
        "x": 0.5,
        "y": 0.5
      },
      "sourceFile": "MissionFailPopup_Continue"
    },
    {
      "type": "Text",
      "fileID": "7780833972455985269",
      "m_FontSize": 50.0,
      "m_Alignment": 4,
      "m_Color": {
        "r": 1.0,
        "g": 1.0,
        "b": 1.0,
        "a": 1.0
      },
      "m_Text": "COTINUE",
      "gameObjectName": "Text",
      "rectSize": {
        "x": 240.0,
        "y": 88.0
      },
      "anchoredPosition": {
        "x": 48.0,
        "y": -4.0
      },
      "anchorMin": {
        "x": 0.5,
        "y": 0.5
      },
      "anchorMax": {
        "x": 0.5,
        "y": 0.5
      },
      "sourceFile": "MissionFailPopup_Continue"
    },
    {
      "type": "Text",
      "fileID": "7780833972550525024",
      "m_FontSize": 40.0,
      "m_Alignment": 4,
      "m_Color": {
        "r": 1.0,
        "g": 1.0,
        "b": 1.0,
        "a": 1.0
      },
      "gameObjectName": "CallToAction",
      "rectSize": {
        "x": 275.0,
        "y": 86.0
      },
      "anchoredPosition": {
        "x": 1.0,
        "y": 0.0
      },
      "anchorMin": {
        "x": 0.5,
        "y": 0.5
      },
      "anchorMax": {
        "x": 0.5,
        "y": 0.5
      },
      "sourceFile": "MissionFailPopup_Continue"
    },
    {
      "type": "Text",
      "fileID": "2496917518695803617",
      "m_FontSize": 30.0,
      "m_Alignment": 3,
      "m_Color": {
        "r": 1.0,
        "g": 1.0,
        "b": 1.0,
        "a": 1.0
      },
      "m_Text": "-500",
      "gameObjectName": "Text",
      "rectSize": {
        "x": 80.0,
        "y": 50.74
      },
      "anchoredPosition": {
        "x": 0.0,
        "y": -46.9
      },
      "anchorMin": {
        "x": 0.5,
        "y": 0.5
      },
      "anchorMax": {
        "x": 0.5,
        "y": 0.5
      },
      "sourceFile": "MissionFailPopup_Continue"
    },
    {
      "type": "Text",
      "fileID": "5257947210746162686",
      "m_FontSize": 70.0,
      "m_Alignment": 4,
      "m_Color": {
        "r": 0.9882353,
        "g": 0.8745098,
        "b": 0.003921569,
        "a": 1.0
      },
      "m_Text": "+5",
      "gameObjectName": "+7",
      "rectSize": {
        "x": 112.7,
        "y": 97.9
      },
      "anchoredPosition": {
        "x": 61.0,
        "y": 19.0
      },
      "anchorMin": {
        "x": 1.0,
        "y": 1.0
      },
      "anchorMax": {
        "x": 1.0,
        "y": 1.0
      },
      "sourceFile": "MissionFailPopup_Continue"
    },
    {
      "type": "Text",
      "fileID": "2265777077086052591",
      "m_FontSize": 40.0,
      "m_Alignment": 4,
      "m_Color": {
        "r": 1.0,
        "g": 0.93483555,
        "b": 0.0,
        "a": 1.0
      },
      "m_Text": "+4",
      "gameObjectName": "Value",
      "rectSize": {
        "x": 146.05,
        "y": 45.16
      },
      "anchoredPosition": {
        "x": -3.61,
        "y": 13.35
      },
      "anchorMin": {
        "x": 0.5,
        "y": 0.5
      },
      "anchorMax": {
        "x": 0.5,
        "y": 0.5
      },
      "sourceFile": "MissionFailPopup_Continue"
    }
  ],
  "layoutGroups": [],
  "contentSizeFitters": [],
  "rectTransformCount": 73
}